{
  "metadata": {
    "sample_data_code": "SD_HUM_PER-MUN_SHEL_OWN_HOME_BULK_v002",
    "label": "Bulk Personal/Municipal Shelter Ownership Options",
    "version": "v002",
    "note": "Bulk fictional sample data for live-style prototype grids."
  },
  "rows": [
    {
      "item": "001",
      "status": "Available",
      "type": "Modular",
      "price": 148500,
      "down": 29700,
      "monthly": 808,
      "location": "Springbrook",
      "fees": "condo fees",
      "condition": "fair",
      "risk": "medium",
      "cvu": 79
    },
    {
      "item": "002",
      "status": "Available",
      "type": "House",
      "price": 227000,
      "down": 45400,
      "monthly": 1235,
      "location": "Penhold",
      "fees": "lot rent",
      "condition": "unknown",
      "risk": "medium",
      "cvu": 77
    },
    {
      "item": "003",
      "status": "Available",
      "type": "Land",
      "price": 80500,
      "down": 16100,
      "monthly": 438,
      "location": "Sylvan Lake",
      "fees": "taxes",
      "condition": "excellent",
      "risk": "high",
      "cvu": 83
    },
    {
      "item": "004",
      "status": "Available",
      "type": "Townhouse",
      "price": 234000,
      "down": 46800,
      "monthly": 1273,
      "location": "Lacombe",
      "fees": "none",
      "condition": "good",
      "risk": "low",
      "cvu": 79
    },
    {
      "item": "005",
      "status": "Available",
      "type": "Condo",
      "price": 112500,
      "down": 22500,
      "monthly": 612,
      "location": "Blackfalds",
      "fees": "condo fees",
      "condition": "fair",
      "risk": "medium",
      "cvu": 84
    },
    {
      "item": "006",
      "status": "Available",
      "type": "Modular",
      "price": 166000,
      "down": 33200,
      "monthly": 903,
      "location": "Innisfail",
      "fees": "lot rent",
      "condition": "unknown",
      "risk": "medium",
      "cvu": 83
    },
    {
      "item": "007",
      "status": "Available",
      "type": "House",
      "price": 244500,
      "down": 48900,
      "monthly": 1330,
      "location": "Calgary Region",
      "fees": "taxes",
      "condition": "excellent",
      "risk": "high",
      "cvu": 82
    },
    {
      "item": "008",
      "status": "Available",
      "type": "Land",
      "price": 98000,
      "down": 19600,
      "monthly": 533,
      "location": "Edmonton Region",
      "fees": "none",
      "condition": "good",
      "risk": "low",
      "cvu": 87
    },
    {
      "item": "009",
      "status": "Available",
      "type": "Townhouse",
      "price": 251500,
      "down": 50300,
      "monthly": 1368,
      "location": "Red Deer",
      "fees": "condo fees",
      "condition": "fair",
      "risk": "medium",
      "cvu": 83
    },
    {
      "item": "010",
      "status": "Watch",
      "type": "Condo",
      "price": 130000,
      "down": 26000,
      "monthly": 707,
      "location": "Springbrook",
      "fees": "lot rent",
      "condition": "unknown",
      "risk": "medium",
      "cvu": 88
    },
    {
      "item": "011",
      "status": "Available",
      "type": "Modular",
      "price": 183500,
      "down": 36700,
      "monthly": 998,
      "location": "Penhold",
      "fees": "taxes",
      "condition": "excellent",
      "risk": "high",
      "cvu": 87
    },
    {
      "item": "012",
      "status": "Available",
      "type": "House",
      "price": 262000,
      "down": 52400,
      "monthly": 1425,
      "location": "Sylvan Lake",
      "fees": "none",
      "condition": "good",
      "risk": "low",
      "cvu": 86
    },
    {
      "item": "013",
      "status": "Available",
      "type": "Land",
      "price": 115500,
      "down": 23100,
      "monthly": 628,
      "location": "Lacombe",
      "fees": "condo fees",
      "condition": "fair",
      "risk": "medium",
      "cvu": 79
    },
    {
      "item": "014",
      "status": "Available",
      "type": "Townhouse",
      "price": 269000,
      "down": 53800,
      "monthly": 1463,
      "location": "Blackfalds",
      "fees": "lot rent",
      "condition": "unknown",
      "risk": "medium",
      "cvu": 75
    },
    {
      "item": "015",
      "status": "Available",
      "type": "Condo",
      "price": 147500,
      "down": 29500,
      "monthly": 802,
      "location": "Innisfail",
      "fees": "taxes",
      "condition": "excellent",
      "risk": "high",
      "cvu": 80
    },
    {
      "item": "016",
      "status": "Available",
      "type": "Modular",
      "price": 201000,
      "down": 40200,
      "monthly": 1093,
      "location": "Calgary Region",
      "fees": "none",
      "condition": "good",
      "risk": "low",
      "cvu": 79
    },
    {
      "item": "017",
      "status": "Available",
      "type": "House",
      "price": 279500,
      "down": 55900,
      "monthly": 1520,
      "location": "Edmonton Region",
      "fees": "condo fees",
      "condition": "fair",
      "risk": "medium",
      "cvu": 78
    },
    {
      "item": "018",
      "status": "Available",
      "type": "Land",
      "price": 133000,
      "down": 26600,
      "monthly": 724,
      "location": "Red Deer",
      "fees": "lot rent",
      "condition": "unknown",
      "risk": "medium",
      "cvu": 83
    },
    {
      "item": "019",
      "status": "Available",
      "type": "Townhouse",
      "price": 286500,
      "down": 57300,
      "monthly": 1559,
      "location": "Springbrook",
      "fees": "taxes",
      "condition": "excellent",
      "risk": "high",
      "cvu": 79
    },
    {
      "item": "020",
      "status": "Watch",
      "type": "Condo",
      "price": 165000,
      "down": 33000,
      "monthly": 898,
      "location": "Penhold",
      "fees": "none",
      "condition": "good",
      "risk": "low",
      "cvu": 84
    },
    {
      "item": "021",
      "status": "Available",
      "type": "Modular",
      "price": 218500,
      "down": 43700,
      "monthly": 1189,
      "location": "Sylvan Lake",
      "fees": "condo fees",
      "condition": "fair",
      "risk": "medium",
      "cvu": 83
    },
    {
      "item": "022",
      "status": "Available",
      "type": "House",
      "price": 297000,
      "down": 59400,
      "monthly": 1616,
      "location": "Lacombe",
      "fees": "lot rent",
      "condition": "unknown",
      "risk": "medium",
      "cvu": 82
    },
    {
      "item": "023",
      "status": "Available",
      "type": "Land",
      "price": 150500,
      "down": 30100,
      "monthly": 819,
      "location": "Blackfalds",
      "fees": "taxes",
      "condition": "excellent",
      "risk": "high",
      "cvu": 87
    },
    {
      "item": "024",
      "status": "Available",
      "type": "Townhouse",
      "price": 304000,
      "down": 60800,
      "monthly": 1654,
      "location": "Innisfail",
      "fees": "none",
      "condition": "good",
      "risk": "low",
      "cvu": 84
    },
    {
      "item": "025",
      "status": "Available",
      "type": "Condo",
      "price": 182500,
      "down": 36500,
      "monthly": 993,
      "location": "Calgary Region",
      "fees": "condo fees",
      "condition": "fair",
      "risk": "medium",
      "cvu": 88
    },
    {
      "item": "026",
      "status": "Available",
      "type": "Modular",
      "price": 236000,
      "down": 47200,
      "monthly": 1284,
      "location": "Edmonton Region",
      "fees": "lot rent",
      "condition": "unknown",
      "risk": "medium",
      "cvu": 75
    },
    {
      "item": "027",
      "status": "Available",
      "type": "House",
      "price": 314500,
      "down": 62900,
      "monthly": 1711,
      "location": "Red Deer",
      "fees": "taxes",
      "condition": "excellent",
      "risk": "high",
      "cvu": 73
    },
    {
      "item": "028",
      "status": "Available",
      "type": "Land",
      "price": 168000,
      "down": 33600,
      "monthly": 914,
      "location": "Springbrook",
      "fees": "none",
      "condition": "good",
      "risk": "low",
      "cvu": 79
    },
    {
      "item": "029",
      "status": "Available",
      "type": "Townhouse",
      "price": 321500,
      "down": 64300,
      "monthly": 1749,
      "location": "Penhold",
      "fees": "condo fees",
      "condition": "fair",
      "risk": "medium",
      "cvu": 75
    },
    {
      "item": "030",
      "status": "Watch",
      "type": "Condo",
      "price": 200000,
      "down": 40000,
      "monthly": 1088,
      "location": "Sylvan Lake",
      "fees": "lot rent",
      "condition": "unknown",
      "risk": "medium",
      "cvu": 80
    },
    {
      "item": "031",
      "status": "Available",
      "type": "Modular",
      "price": 253500,
      "down": 50700,
      "monthly": 1379,
      "location": "Lacombe",
      "fees": "taxes",
      "condition": "excellent",
      "risk": "high",
      "cvu": 79
    },
    {
      "item": "032",
      "status": "Available",
      "type": "House",
      "price": 332000,
      "down": 66400,
      "monthly": 1806,
      "location": "Blackfalds",
      "fees": "none",
      "condition": "good",
      "risk": "low",
      "cvu": 78
    },
    {
      "item": "033",
      "status": "Available",
      "type": "Land",
      "price": 185500,
      "down": 37100,
      "monthly": 1009,
      "location": "Innisfail",
      "fees": "condo fees",
      "condition": "fair",
      "risk": "medium",
      "cvu": 83
    },
    {
      "item": "034",
      "status": "Available",
      "type": "Townhouse",
      "price": 339000,
      "down": 67800,
      "monthly": 1844,
      "location": "Calgary Region",
      "fees": "lot rent",
      "condition": "unknown",
      "risk": "medium",
      "cvu": 80
    },
    {
      "item": "035",
      "status": "Available",
      "type": "Condo",
      "price": 217500,
      "down": 43500,
      "monthly": 1183,
      "location": "Edmonton Region",
      "fees": "taxes",
      "condition": "excellent",
      "risk": "high",
      "cvu": 84
    },
    {
      "item": "036",
      "status": "Available",
      "type": "Modular",
      "price": 271000,
      "down": 54200,
      "monthly": 1474,
      "location": "Red Deer",
      "fees": "none",
      "condition": "good",
      "risk": "low",
      "cvu": 84
    },
    {
      "item": "037",
      "status": "Available",
      "type": "House",
      "price": 220000,
      "down": 44000,
      "monthly": 1197,
      "location": "Springbrook",
      "fees": "condo fees",
      "condition": "fair",
      "risk": "medium",
      "cvu": 86
    },
    {
      "item": "038",
      "status": "Available",
      "type": "Land",
      "price": 73500,
      "down": 14700,
      "monthly": 400,
      "location": "Penhold",
      "fees": "lot rent",
      "condition": "unknown",
      "risk": "medium",
      "cvu": 92
    },
    {
      "item": "039",
      "status": "Available",
      "type": "Townhouse",
      "price": 227000,
      "down": 45400,
      "monthly": 1235,
      "location": "Sylvan Lake",
      "fees": "taxes",
      "condition": "excellent",
      "risk": "high",
      "cvu": 75
    },
    {
      "item": "040",
      "status": "Watch",
      "type": "Condo",
      "price": 105500,
      "down": 21100,
      "monthly": 574,
      "location": "Lacombe",
      "fees": "none",
      "condition": "good",
      "risk": "low",
      "cvu": 80
    },
    {
      "item": "041",
      "status": "Available",
      "type": "Modular",
      "price": 159000,
      "down": 31800,
      "monthly": 865,
      "location": "Blackfalds",
      "fees": "condo fees",
      "condition": "fair",
      "risk": "medium",
      "cvu": 79
    },
    {
      "item": "042",
      "status": "Available",
      "type": "House",
      "price": 237500,
      "down": 47500,
      "monthly": 1292,
      "location": "Innisfail",
      "fees": "lot rent",
      "condition": "unknown",
      "risk": "medium",
      "cvu": 78
    },
    {
      "item": "043",
      "status": "Available",
      "type": "Land",
      "price": 91000,
      "down": 18200,
      "monthly": 495,
      "location": "Calgary Region",
      "fees": "taxes",
      "condition": "excellent",
      "risk": "high",
      "cvu": 83
    },
    {
      "item": "044",
      "status": "Available",
      "type": "Townhouse",
      "price": 244500,
      "down": 48900,
      "monthly": 1330,
      "location": "Edmonton Region",
      "fees": "none",
      "condition": "good",
      "risk": "low",
      "cvu": 80
    },
    {
      "item": "045",
      "status": "Available",
      "type": "Condo",
      "price": 123000,
      "down": 24600,
      "monthly": 669,
      "location": "Red Deer",
      "fees": "condo fees",
      "condition": "fair",
      "risk": "medium",
      "cvu": 84
    },
    {
      "item": "046",
      "status": "Available",
      "type": "Modular",
      "price": 176500,
      "down": 35300,
      "monthly": 960,
      "location": "Springbrook",
      "fees": "lot rent",
      "condition": "unknown",
      "risk": "medium",
      "cvu": 84
    },
    {
      "item": "047",
      "status": "Available",
      "type": "House",
      "price": 255000,
      "down": 51000,
      "monthly": 1387,
      "location": "Penhold",
      "fees": "taxes",
      "condition": "excellent",
      "risk": "high",
      "cvu": 82
    },
    {
      "item": "048",
      "status": "Available",
      "type": "Land",
      "price": 108500,
      "down": 21700,
      "monthly": 590,
      "location": "Sylvan Lake",
      "fees": "none",
      "condition": "good",
      "risk": "low",
      "cvu": 88
    },
    {
      "item": "049",
      "status": "Available",
      "type": "Townhouse",
      "price": 262000,
      "down": 52400,
      "monthly": 1425,
      "location": "Lacombe",
      "fees": "condo fees",
      "condition": "fair",
      "risk": "medium",
      "cvu": 84
    },
    {
      "item": "050",
      "status": "Watch",
      "type": "Condo",
      "price": 140500,
      "down": 28100,
      "monthly": 764,
      "location": "Blackfalds",
      "fees": "lot rent",
      "condition": "unknown",
      "risk": "medium",
      "cvu": 89
    },
    {
      "item": "051",
      "status": "Available",
      "type": "Modular",
      "price": 194000,
      "down": 38800,
      "monthly": 1055,
      "location": "Innisfail",
      "fees": "taxes",
      "condition": "excellent",
      "risk": "high",
      "cvu": 88
    },
    {
      "item": "052",
      "status": "Available",
      "type": "House",
      "price": 272500,
      "down": 54500,
      "monthly": 1482,
      "location": "Calgary Region",
      "fees": "none",
      "condition": "good",
      "risk": "low",
      "cvu": 74
    },
    {
      "item": "053",
      "status": "Available",
      "type": "Land",
      "price": 126000,
      "down": 25200,
      "monthly": 685,
      "location": "Edmonton Region",
      "fees": "condo fees",
      "condition": "fair",
      "risk": "medium",
      "cvu": 79
    },
    {
      "item": "054",
      "status": "Available",
      "type": "Townhouse",
      "price": 279500,
      "down": 55900,
      "monthly": 1520,
      "location": "Red Deer",
      "fees": "lot rent",
      "condition": "unknown",
      "risk": "medium",
      "cvu": 76
    },
    {
      "item": "055",
      "status": "Available",
      "type": "Condo",
      "price": 158000,
      "down": 31600,
      "monthly": 860,
      "location": "Springbrook",
      "fees": "taxes",
      "condition": "excellent",
      "risk": "high",
      "cvu": 80
    },
    {
      "item": "056",
      "status": "Available",
      "type": "Modular",
      "price": 211500,
      "down": 42300,
      "monthly": 1151,
      "location": "Penhold",
      "fees": "none",
      "condition": "good",
      "risk": "low",
      "cvu": 80
    },
    {
      "item": "057",
      "status": "Available",
      "type": "House",
      "price": 290000,
      "down": 58000,
      "monthly": 1578,
      "location": "Sylvan Lake",
      "fees": "condo fees",
      "condition": "fair",
      "risk": "medium",
      "cvu": 78
    },
    {
      "item": "058",
      "status": "Available",
      "type": "Land",
      "price": 143500,
      "down": 28700,
      "monthly": 781,
      "location": "Lacombe",
      "fees": "lot rent",
      "condition": "unknown",
      "risk": "medium",
      "cvu": 84
    },
    {
      "item": "059",
      "status": "Available",
      "type": "Townhouse",
      "price": 297000,
      "down": 59400,
      "monthly": 1616,
      "location": "Blackfalds",
      "fees": "taxes",
      "condition": "excellent",
      "risk": "high",
      "cvu": 80
    },
    {
      "item": "060",
      "status": "Watch",
      "type": "Condo",
      "price": 175500,
      "down": 35100,
      "monthly": 955,
      "location": "Innisfail",
      "fees": "none",
      "condition": "good",
      "risk": "low",
      "cvu": 85
    },
    {
      "item": "061",
      "status": "Available",
      "type": "Modular",
      "price": 229000,
      "down": 45800,
      "monthly": 1246,
      "location": "Calgary Region",
      "fees": "condo fees",
      "condition": "fair",
      "risk": "medium",
      "cvu": 84
    },
    {
      "item": "062",
      "status": "Available",
      "type": "House",
      "price": 307500,
      "down": 61500,
      "monthly": 1673,
      "location": "Edmonton Region",
      "fees": "lot rent",
      "condition": "unknown",
      "risk": "medium",
      "cvu": 83
    },
    {
      "item": "063",
      "status": "Available",
      "type": "Land",
      "price": 161000,
      "down": 32200,
      "monthly": 876,
      "location": "Red Deer",
      "fees": "taxes",
      "condition": "excellent",
      "risk": "high",
      "cvu": 88
    },
    {
      "item": "064",
      "status": "Available",
      "type": "Townhouse",
      "price": 314500,
      "down": 62900,
      "monthly": 1711,
      "location": "Springbrook",
      "fees": "none",
      "condition": "good",
      "risk": "low",
      "cvu": 84
    },
    {
      "item": "065",
      "status": "Available",
      "type": "Condo",
      "price": 193000,
      "down": 38600,
      "monthly": 1050,
      "location": "Penhold",
      "fees": "condo fees",
      "condition": "fair",
      "risk": "medium",
      "cvu": 76
    },
    {
      "item": "066",
      "status": "Available",
      "type": "Modular",
      "price": 246500,
      "down": 49300,
      "monthly": 1341,
      "location": "Sylvan Lake",
      "fees": "lot rent",
      "condition": "unknown",
      "risk": "medium",
      "cvu": 76
    },
    {
      "item": "067",
      "status": "Available",
      "type": "House",
      "price": 325000,
      "down": 65000,
      "monthly": 1768,
      "location": "Lacombe",
      "fees": "taxes",
      "condition": "excellent",
      "risk": "high",
      "cvu": 74
    },
    {
      "item": "068",
      "status": "Available",
      "type": "Land",
      "price": 178500,
      "down": 35700,
      "monthly": 971,
      "location": "Blackfalds",
      "fees": "none",
      "condition": "good",
      "risk": "low",
      "cvu": 80
    },
    {
      "item": "069",
      "status": "Available",
      "type": "Townhouse",
      "price": 332000,
      "down": 66400,
      "monthly": 1806,
      "location": "Innisfail",
      "fees": "condo fees",
      "condition": "fair",
      "risk": "medium",
      "cvu": 76
    },
    {
      "item": "070",
      "status": "Watch",
      "type": "Condo",
      "price": 210500,
      "down": 42100,
      "monthly": 1145,
      "location": "Calgary Region",
      "fees": "lot rent",
      "condition": "unknown",
      "risk": "medium",
      "cvu": 81
    },
    {
      "item": "071",
      "status": "Available",
      "type": "Modular",
      "price": 264000,
      "down": 52800,
      "monthly": 1436,
      "location": "Edmonton Region",
      "fees": "taxes",
      "condition": "excellent",
      "risk": "high",
      "cvu": 80
    },
    {
      "item": "072",
      "status": "Available",
      "type": "House",
      "price": 342500,
      "down": 68500,
      "monthly": 1863,
      "location": "Red Deer",
      "fees": "none",
      "condition": "good",
      "risk": "low",
      "cvu": 79
    },
    {
      "item": "073",
      "status": "Available",
      "type": "Land",
      "price": 196000,
      "down": 39200,
      "monthly": 1066,
      "location": "Springbrook",
      "fees": "condo fees",
      "condition": "fair",
      "risk": "medium",
      "cvu": 84
    },
    {
      "item": "074",
      "status": "Available",
      "type": "Townhouse",
      "price": 220000,
      "down": 44000,
      "monthly": 1197,
      "location": "Penhold",
      "fees": "lot rent",
      "condition": "unknown",
      "risk": "medium",
      "cvu": 84
    },
    {
      "item": "075",
      "status": "Available",
      "type": "Condo",
      "price": 98500,
      "down": 19700,
      "monthly": 536,
      "location": "Sylvan Lake",
      "fees": "taxes",
      "condition": "excellent",
      "risk": "high",
      "cvu": 89
    },
    {
      "item": "076",
      "status": "Available",
      "type": "Modular",
      "price": 152000,
      "down": 30400,
      "monthly": 827,
      "location": "Lacombe",
      "fees": "none",
      "condition": "good",
      "risk": "low",
      "cvu": 88
    },
    {
      "item": "077",
      "status": "Available",
      "type": "House",
      "price": 230500,
      "down": 46100,
      "monthly": 1254,
      "location": "Blackfalds",
      "fees": "condo fees",
      "condition": "fair",
      "risk": "medium",
      "cvu": 87
    },
    {
      "item": "078",
      "status": "Available",
      "type": "Land",
      "price": 84000,
      "down": 16800,
      "monthly": 457,
      "location": "Innisfail",
      "fees": "lot rent",
      "condition": "unknown",
      "risk": "medium",
      "cvu": 79
    },
    {
      "item": "079",
      "status": "Available",
      "type": "Townhouse",
      "price": 237500,
      "down": 47500,
      "monthly": 1292,
      "location": "Calgary Region",
      "fees": "taxes",
      "condition": "excellent",
      "risk": "high",
      "cvu": 76
    },
    {
      "item": "080",
      "status": "Watch",
      "type": "Condo",
      "price": 116000,
      "down": 23200,
      "monthly": 631,
      "location": "Edmonton Region",
      "fees": "none",
      "condition": "good",
      "risk": "low",
      "cvu": 80
    },
    {
      "item": "081",
      "status": "Available",
      "type": "Modular",
      "price": 169500,
      "down": 33900,
      "monthly": 922,
      "location": "Red Deer",
      "fees": "condo fees",
      "condition": "fair",
      "risk": "medium",
      "cvu": 80
    },
    {
      "item": "082",
      "status": "Available",
      "type": "House",
      "price": 248000,
      "down": 49600,
      "monthly": 1349,
      "location": "Springbrook",
      "fees": "lot rent",
      "condition": "unknown",
      "risk": "medium",
      "cvu": 79
    },
    {
      "item": "083",
      "status": "Available",
      "type": "Land",
      "price": 101500,
      "down": 20300,
      "monthly": 552,
      "location": "Penhold",
      "fees": "taxes",
      "condition": "excellent",
      "risk": "high",
      "cvu": 84
    },
    {
      "item": "084",
      "status": "Available",
      "type": "Townhouse",
      "price": 255000,
      "down": 51000,
      "monthly": 1387,
      "location": "Sylvan Lake",
      "fees": "none",
      "condition": "good",
      "risk": "low",
      "cvu": 80
    },
    {
      "item": "085",
      "status": "Available",
      "type": "Condo",
      "price": 133500,
      "down": 26700,
      "monthly": 726,
      "location": "Lacombe",
      "fees": "condo fees",
      "condition": "fair",
      "risk": "medium",
      "cvu": 85
    },
    {
      "item": "086",
      "status": "Available",
      "type": "Modular",
      "price": 187000,
      "down": 37400,
      "monthly": 1017,
      "location": "Blackfalds",
      "fees": "lot rent",
      "condition": "unknown",
      "risk": "medium",
      "cvu": 84
    },
    {
      "item": "087",
      "status": "Available",
      "type": "House",
      "price": 265500,
      "down": 53100,
      "monthly": 1444,
      "location": "Innisfail",
      "fees": "taxes",
      "condition": "excellent",
      "risk": "high",
      "cvu": 83
    },
    {
      "item": "088",
      "status": "Available",
      "type": "Land",
      "price": 119000,
      "down": 23800,
      "monthly": 647,
      "location": "Calgary Region",
      "fees": "none",
      "condition": "good",
      "risk": "low",
      "cvu": 88
    },
    {
      "item": "089",
      "status": "Available",
      "type": "Townhouse",
      "price": 272500,
      "down": 54500,
      "monthly": 1482,
      "location": "Edmonton Region",
      "fees": "condo fees",
      "condition": "fair",
      "risk": "medium",
      "cvu": 85
    },
    {
      "item": "090",
      "status": "Watch",
      "type": "Condo",
      "price": 151000,
      "down": 30200,
      "monthly": 821,
      "location": "Red Deer",
      "fees": "lot rent",
      "condition": "unknown",
      "risk": "medium",
      "cvu": 89
    },
    {
      "item": "091",
      "status": "Available",
      "type": "Modular",
      "price": 204500,
      "down": 40900,
      "monthly": 1112,
      "location": "Springbrook",
      "fees": "taxes",
      "condition": "excellent",
      "risk": "high",
      "cvu": 76
    },
    {
      "item": "092",
      "status": "Available",
      "type": "House",
      "price": 283000,
      "down": 56600,
      "monthly": 1540,
      "location": "Penhold",
      "fees": "none",
      "condition": "good",
      "risk": "low",
      "cvu": 74
    },
    {
      "item": "093",
      "status": "Available",
      "type": "Land",
      "price": 136500,
      "down": 27300,
      "monthly": 743,
      "location": "Sylvan Lake",
      "fees": "condo fees",
      "condition": "fair",
      "risk": "medium",
      "cvu": 80
    },
    {
      "item": "094",
      "status": "Available",
      "type": "Townhouse",
      "price": 290000,
      "down": 58000,
      "monthly": 1578,
      "location": "Lacombe",
      "fees": "lot rent",
      "condition": "unknown",
      "risk": "medium",
      "cvu": 76
    },
    {
      "item": "095",
      "status": "Available",
      "type": "Condo",
      "price": 168500,
      "down": 33700,
      "monthly": 917,
      "location": "Blackfalds",
      "fees": "taxes",
      "condition": "excellent",
      "risk": "high",
      "cvu": 81
    },
    {
      "item": "096",
      "status": "Available",
      "type": "Modular",
      "price": 222000,
      "down": 44400,
      "monthly": 1208,
      "location": "Innisfail",
      "fees": "none",
      "condition": "good",
      "risk": "low",
      "cvu": 80
    },
    {
      "item": "097",
      "status": "Available",
      "type": "House",
      "price": 300500,
      "down": 60100,
      "monthly": 1635,
      "location": "Calgary Region",
      "fees": "condo fees",
      "condition": "fair",
      "risk": "medium",
      "cvu": 79
    },
    {
      "item": "098",
      "status": "Available",
      "type": "Land",
      "price": 154000,
      "down": 30800,
      "monthly": 838,
      "location": "Edmonton Region",
      "fees": "lot rent",
      "condition": "unknown",
      "risk": "medium",
      "cvu": 84
    },
    {
      "item": "099",
      "status": "Available",
      "type": "Townhouse",
      "price": 307500,
      "down": 61500,
      "monthly": 1673,
      "location": "Red Deer",
      "fees": "taxes",
      "condition": "excellent",
      "risk": "high",
      "cvu": 81
    },
    {
      "item": "100",
      "status": "Watch",
      "type": "Condo",
      "price": 186000,
      "down": 37200,
      "monthly": 1012,
      "location": "Springbrook",
      "fees": "none",
      "condition": "good",
      "risk": "low",
      "cvu": 85
    },
    {
      "item": "101",
      "status": "Available",
      "type": "Modular",
      "price": 239500,
      "down": 47900,
      "monthly": 1303,
      "location": "Penhold",
      "fees": "condo fees",
      "condition": "fair",
      "risk": "medium",
      "cvu": 85
    },
    {
      "item": "102",
      "status": "Available",
      "type": "House",
      "price": 318000,
      "down": 63600,
      "monthly": 1730,
      "location": "Sylvan Lake",
      "fees": "lot rent",
      "condition": "unknown",
      "risk": "medium",
      "cvu": 83
    },
    {
      "item": "103",
      "status": "Available",
      "type": "Land",
      "price": 171500,
      "down": 34300,
      "monthly": 933,
      "location": "Lacombe",
      "fees": "taxes",
      "condition": "excellent",
      "risk": "high",
      "cvu": 89
    },
    {
      "item": "104",
      "status": "Available",
      "type": "Townhouse",
      "price": 325000,
      "down": 65000,
      "monthly": 1768,
      "location": "Blackfalds",
      "fees": "none",
      "condition": "good",
      "risk": "low",
      "cvu": 72
    },
    {
      "item": "105",
      "status": "Available",
      "type": "Condo",
      "price": 203500,
      "down": 40700,
      "monthly": 1107,
      "location": "Innisfail",
      "fees": "condo fees",
      "condition": "fair",
      "risk": "medium",
      "cvu": 77
    },
    {
      "item": "106",
      "status": "Available",
      "type": "Modular",
      "price": 257000,
      "down": 51400,
      "monthly": 1398,
      "location": "Calgary Region",
      "fees": "lot rent",
      "condition": "unknown",
      "risk": "medium",
      "cvu": 76
    },
    {
      "item": "107",
      "status": "Available",
      "type": "House",
      "price": 335500,
      "down": 67100,
      "monthly": 1825,
      "location": "Edmonton Region",
      "fees": "taxes",
      "condition": "excellent",
      "risk": "high",
      "cvu": 75
    },
    {
      "item": "108",
      "status": "Available",
      "type": "Land",
      "price": 189000,
      "down": 37800,
      "monthly": 1028,
      "location": "Red Deer",
      "fees": "none",
      "condition": "good",
      "risk": "low",
      "cvu": 80
    },
    {
      "item": "109",
      "status": "Available",
      "type": "Townhouse",
      "price": 342500,
      "down": 68500,
      "monthly": 1863,
      "location": "Springbrook",
      "fees": "condo fees",
      "condition": "fair",
      "risk": "medium",
      "cvu": 77
    },
    {
      "item": "110",
      "status": "Watch",
      "type": "Condo",
      "price": 221000,
      "down": 44200,
      "monthly": 1202,
      "location": "Penhold",
      "fees": "lot rent",
      "condition": "unknown",
      "risk": "medium",
      "cvu": 81
    },
    {
      "item": "111",
      "status": "Available",
      "type": "Modular",
      "price": 145000,
      "down": 29000,
      "monthly": 789,
      "location": "Sylvan Lake",
      "fees": "taxes",
      "condition": "excellent",
      "risk": "high",
      "cvu": 85
    },
    {
      "item": "112",
      "status": "Available",
      "type": "House",
      "price": 223500,
      "down": 44700,
      "monthly": 1216,
      "location": "Lacombe",
      "fees": "none",
      "condition": "good",
      "risk": "low",
      "cvu": 83
    },
    {
      "item": "113",
      "status": "Available",
      "type": "Land",
      "price": 77000,
      "down": 15400,
      "monthly": 419,
      "location": "Blackfalds",
      "fees": "condo fees",
      "condition": "fair",
      "risk": "medium",
      "cvu": 89
    },
    {
      "item": "114",
      "status": "Available",
      "type": "Townhouse",
      "price": 230500,
      "down": 46100,
      "monthly": 1254,
      "location": "Innisfail",
      "fees": "lot rent",
      "condition": "unknown",
      "risk": "medium",
      "cvu": 85
    },
    {
      "item": "115",
      "status": "Available",
      "type": "Condo",
      "price": 109000,
      "down": 21800,
      "monthly": 593,
      "location": "Calgary Region",
      "fees": "taxes",
      "condition": "excellent",
      "risk": "high",
      "cvu": 90
    },
    {
      "item": "116",
      "status": "Available",
      "type": "Modular",
      "price": 162500,
      "down": 32500,
      "monthly": 884,
      "location": "Edmonton Region",
      "fees": "none",
      "condition": "good",
      "risk": "low",
      "cvu": 89
    },
    {
      "item": "117",
      "status": "Available",
      "type": "House",
      "price": 241000,
      "down": 48200,
      "monthly": 1311,
      "location": "Red Deer",
      "fees": "condo fees",
      "condition": "fair",
      "risk": "medium",
      "cvu": 75
    },
    {
      "item": "118",
      "status": "Available",
      "type": "Land",
      "price": 94500,
      "down": 18900,
      "monthly": 514,
      "location": "Springbrook",
      "fees": "lot rent",
      "condition": "unknown",
      "risk": "medium",
      "cvu": 80
    },
    {
      "item": "119",
      "status": "Available",
      "type": "Townhouse",
      "price": 248000,
      "down": 49600,
      "monthly": 1349,
      "location": "Penhold",
      "fees": "taxes",
      "condition": "excellent",
      "risk": "high",
      "cvu": 77
    },
    {
      "item": "120",
      "status": "Watch",
      "type": "Condo",
      "price": 126500,
      "down": 25300,
      "monthly": 688,
      "location": "Sylvan Lake",
      "fees": "none",
      "condition": "good",
      "risk": "low",
      "cvu": 81
    },
    {
      "item": "121",
      "status": "Available",
      "type": "Modular",
      "price": 180000,
      "down": 36000,
      "monthly": 979,
      "location": "Lacombe",
      "fees": "condo fees",
      "condition": "fair",
      "risk": "medium",
      "cvu": 81
    },
    {
      "item": "122",
      "status": "Available",
      "type": "House",
      "price": 258500,
      "down": 51700,
      "monthly": 1406,
      "location": "Blackfalds",
      "fees": "lot rent",
      "condition": "unknown",
      "risk": "medium",
      "cvu": 79
    },
    {
      "item": "123",
      "status": "Available",
      "type": "Land",
      "price": 112000,
      "down": 22400,
      "monthly": 609,
      "location": "Innisfail",
      "fees": "taxes",
      "condition": "excellent",
      "risk": "high",
      "cvu": 85
    },
    {
      "item": "124",
      "status": "Available",
      "type": "Townhouse",
      "price": 265500,
      "down": 53100,
      "monthly": 1444,
      "location": "Calgary Region",
      "fees": "none",
      "condition": "good",
      "risk": "low",
      "cvu": 81
    },
    {
      "item": "125",
      "status": "Available",
      "type": "Condo",
      "price": 144000,
      "down": 28800,
      "monthly": 783,
      "location": "Edmonton Region",
      "fees": "condo fees",
      "condition": "fair",
      "risk": "medium",
      "cvu": 86
    },
    {
      "item": "126",
      "status": "Available",
      "type": "Modular",
      "price": 197500,
      "down": 39500,
      "monthly": 1074,
      "location": "Red Deer",
      "fees": "lot rent",
      "condition": "unknown",
      "risk": "medium",
      "cvu": 85
    },
    {
      "item": "127",
      "status": "Available",
      "type": "House",
      "price": 276000,
      "down": 55200,
      "monthly": 1501,
      "location": "Springbrook",
      "fees": "taxes",
      "condition": "excellent",
      "risk": "high",
      "cvu": 84
    },
    {
      "item": "128",
      "status": "Available",
      "type": "Land",
      "price": 129500,
      "down": 25900,
      "monthly": 704,
      "location": "Penhold",
      "fees": "none",
      "condition": "good",
      "risk": "low",
      "cvu": 89
    },
    {
      "item": "129",
      "status": "Available",
      "type": "Townhouse",
      "price": 283000,
      "down": 56600,
      "monthly": 1540,
      "location": "Sylvan Lake",
      "fees": "condo fees",
      "condition": "fair",
      "risk": "medium",
      "cvu": 85
    },
    {
      "item": "130",
      "status": "Watch",
      "type": "Condo",
      "price": 161500,
      "down": 32300,
      "monthly": 879,
      "location": "Lacombe",
      "fees": "lot rent",
      "condition": "unknown",
      "risk": "medium",
      "cvu": 77
    },
    {
      "item": "131",
      "status": "Available",
      "type": "Modular",
      "price": 215000,
      "down": 43000,
      "monthly": 1170,
      "location": "Blackfalds",
      "fees": "taxes",
      "condition": "excellent",
      "risk": "high",
      "cvu": 76
    },
    {
      "item": "132",
      "status": "Available",
      "type": "House",
      "price": 293500,
      "down": 58700,
      "monthly": 1597,
      "location": "Innisfail",
      "fees": "none",
      "condition": "good",
      "risk": "low",
      "cvu": 75
    },
    {
      "item": "133",
      "status": "Available",
      "type": "Land",
      "price": 147000,
      "down": 29400,
      "monthly": 800,
      "location": "Calgary Region",
      "fees": "condo fees",
      "condition": "fair",
      "risk": "medium",
      "cvu": 81
    },
    {
      "item": "134",
      "status": "Available",
      "type": "Townhouse",
      "price": 300500,
      "down": 60100,
      "monthly": 1635,
      "location": "Edmonton Region",
      "fees": "lot rent",
      "condition": "unknown",
      "risk": "medium",
      "cvu": 77
    },
    {
      "item": "135",
      "status": "Available",
      "type": "Condo",
      "price": 179000,
      "down": 35800,
      "monthly": 974,
      "location": "Red Deer",
      "fees": "taxes",
      "condition": "excellent",
      "risk": "high",
      "cvu": 82
    },
    {
      "item": "136",
      "status": "Available",
      "type": "Modular",
      "price": 232500,
      "down": 46500,
      "monthly": 1265,
      "location": "Springbrook",
      "fees": "none",
      "condition": "good",
      "risk": "low",
      "cvu": 81
    },
    {
      "item": "137",
      "status": "Available",
      "type": "House",
      "price": 311000,
      "down": 62200,
      "monthly": 1692,
      "location": "Penhold",
      "fees": "condo fees",
      "condition": "fair",
      "risk": "medium",
      "cvu": 80
    },
    {
      "item": "138",
      "status": "Available",
      "type": "Land",
      "price": 164500,
      "down": 32900,
      "monthly": 895,
      "location": "Sylvan Lake",
      "fees": "lot rent",
      "condition": "unknown",
      "risk": "medium",
      "cvu": 85
    },
    {
      "item": "139",
      "status": "Available",
      "type": "Townhouse",
      "price": 318000,
      "down": 63600,
      "monthly": 1730,
      "location": "Lacombe",
      "fees": "taxes",
      "condition": "excellent",
      "risk": "high",
      "cvu": 81
    },
    {
      "item": "140",
      "status": "Watch",
      "type": "Condo",
      "price": 196500,
      "down": 39300,
      "monthly": 1069,
      "location": "Blackfalds",
      "fees": "none",
      "condition": "good",
      "risk": "low",
      "cvu": 86
    },
    {
      "item": "141",
      "status": "Available",
      "type": "Modular",
      "price": 250000,
      "down": 50000,
      "monthly": 1360,
      "location": "Innisfail",
      "fees": "condo fees",
      "condition": "fair",
      "risk": "medium",
      "cvu": 85
    },
    {
      "item": "142",
      "status": "Available",
      "type": "House",
      "price": 328500,
      "down": 65700,
      "monthly": 1787,
      "location": "Calgary Region",
      "fees": "lot rent",
      "condition": "unknown",
      "risk": "medium",
      "cvu": 84
    },
    {
      "item": "143",
      "status": "Available",
      "type": "Land",
      "price": 182000,
      "down": 36400,
      "monthly": 990,
      "location": "Edmonton Region",
      "fees": "taxes",
      "condition": "excellent",
      "risk": "high",
      "cvu": 76
    },
    {
      "item": "144",
      "status": "Available",
      "type": "Townhouse",
      "price": 335500,
      "down": 67100,
      "monthly": 1825,
      "location": "Red Deer",
      "fees": "none",
      "condition": "good",
      "risk": "low",
      "cvu": 73
    },
    {
      "item": "145",
      "status": "Available",
      "type": "Condo",
      "price": 214000,
      "down": 42800,
      "monthly": 1164,
      "location": "Springbrook",
      "fees": "condo fees",
      "condition": "fair",
      "risk": "medium",
      "cvu": 78
    },
    {
      "item": "146",
      "status": "Available",
      "type": "Modular",
      "price": 267500,
      "down": 53500,
      "monthly": 1455,
      "location": "Penhold",
      "fees": "lot rent",
      "condition": "unknown",
      "risk": "medium",
      "cvu": 77
    },
    {
      "item": "147",
      "status": "Available",
      "type": "House",
      "price": 346000,
      "down": 69200,
      "monthly": 1882,
      "location": "Sylvan Lake",
      "fees": "taxes",
      "condition": "excellent",
      "risk": "high",
      "cvu": 76
    },
    {
      "item": "148",
      "status": "Available",
      "type": "Land",
      "price": 70000,
      "down": 14000,
      "monthly": 381,
      "location": "Lacombe",
      "fees": "none",
      "condition": "good",
      "risk": "low",
      "cvu": 85
    },
    {
      "item": "149",
      "status": "Available",
      "type": "Townhouse",
      "price": 223500,
      "down": 44700,
      "monthly": 1216,
      "location": "Blackfalds",
      "fees": "condo fees",
      "condition": "fair",
      "risk": "medium",
      "cvu": 81
    },
    {
      "item": "150",
      "status": "Watch",
      "type": "Condo",
      "price": 102000,
      "down": 20400,
      "monthly": 555,
      "location": "Innisfail",
      "fees": "lot rent",
      "condition": "unknown",
      "risk": "medium",
      "cvu": 86
    },
    {
      "item": "151",
      "status": "Available",
      "type": "Modular",
      "price": 155500,
      "down": 31100,
      "monthly": 846,
      "location": "Calgary Region",
      "fees": "taxes",
      "condition": "excellent",
      "risk": "high",
      "cvu": 85
    },
    {
      "item": "152",
      "status": "Available",
      "type": "House",
      "price": 234000,
      "down": 46800,
      "monthly": 1273,
      "location": "Edmonton Region",
      "fees": "none",
      "condition": "good",
      "risk": "low",
      "cvu": 84
    },
    {
      "item": "153",
      "status": "Available",
      "type": "Land",
      "price": 87500,
      "down": 17500,
      "monthly": 476,
      "location": "Red Deer",
      "fees": "condo fees",
      "condition": "fair",
      "risk": "medium",
      "cvu": 89
    },
    {
      "item": "154",
      "status": "Available",
      "type": "Townhouse",
      "price": 241000,
      "down": 48200,
      "monthly": 1311,
      "location": "Springbrook",
      "fees": "lot rent",
      "condition": "unknown",
      "risk": "medium",
      "cvu": 86
    },
    {
      "item": "155",
      "status": "Available",
      "type": "Condo",
      "price": 119500,
      "down": 23900,
      "monthly": 650,
      "location": "Penhold",
      "fees": "taxes",
      "condition": "excellent",
      "risk": "high",
      "cvu": 90
    },
    {
      "item": "156",
      "status": "Available",
      "type": "Modular",
      "price": 173000,
      "down": 34600,
      "monthly": 941,
      "location": "Sylvan Lake",
      "fees": "none",
      "condition": "good",
      "risk": "low",
      "cvu": 77
    },
    {
      "item": "157",
      "status": "Available",
      "type": "House",
      "price": 251500,
      "down": 50300,
      "monthly": 1368,
      "location": "Lacombe",
      "fees": "condo fees",
      "condition": "fair",
      "risk": "medium",
      "cvu": 75
    },
    {
      "item": "158",
      "status": "Available",
      "type": "Land",
      "price": 105000,
      "down": 21000,
      "monthly": 571,
      "location": "Blackfalds",
      "fees": "lot rent",
      "condition": "unknown",
      "risk": "medium",
      "cvu": 81
    },
    {
      "item": "159",
      "status": "Available",
      "type": "Townhouse",
      "price": 258500,
      "down": 51700,
      "monthly": 1406,
      "location": "Innisfail",
      "fees": "taxes",
      "condition": "excellent",
      "risk": "high",
      "cvu": 77
    },
    {
      "item": "160",
      "status": "Watch",
      "type": "Condo",
      "price": 137000,
      "down": 27400,
      "monthly": 745,
      "location": "Calgary Region",
      "fees": "none",
      "condition": "good",
      "risk": "low",
      "cvu": 82
    }
  ]
}